<?xml version="1.0" encoding="iso-8859-1"?>
<!DOCTYPE character PUBLIC "-//rpgprofiler.net//DTD 3EProfiler 1.0//EN"
  "http://www.rpgprofiler.net/2003/3EProfiler.dtd">
<character xmlns="http://www.rpgprofiler.net/2003/3EProfiler">
  <source>http://www.dndsheets.net/</source>
  <cname>Keldarn</cname>
  <template>Pathfinder Beta</template>
  <public>y</public>
  <data>
    <node name="firstload">false</node>
    <node name="LastSaveDate">22 October 2009 19:46:51</node>
    <node name="Name">Keldarn Shield-arm</node>
    <node name="Player">Shane</node>
    <node name="XPCurrent">3000</node>
    <node name="XPNext">6000</node>
    <node name="Class">Fighter</node>
    <node name="Race">Dwarf</node>
    <node name="Alignment">LG</node>
    <node name="Level">2</node>
    <node name="Size">Medium</node>
    <node name="Gender">Male</node>
    <node name="Str">16</node>
    <node name="StrMod">+3</node>
    <node name="Dex">12</node>
    <node name="DexMod">+1</node>
    <node name="Con">19</node>
    <node name="ConMod">+4</node>
    <node name="Int">14</node>
    <node name="IntMod">+2</node>
    <node name="Wis">12</node>
    <node name="WisMod">+1</node>
    <node name="Cha">10</node>
    <node name="ChaMod">0</node>
    <node name="AP">CMD 16</node>
    <node name="HP">28</node>
    <node name="HPWounds">28</node>
    <node name="AC">21</node>
    <node name="ACArmor">6</node>
    <node name="ACShield">4</node>
    <node name="ACOther">0</node>
    <node name="ACDex">1</node>
    <node name="ACSize">0</node>
    <node name="ACNat">0</node>
    <node name="ACDeflect">0</node>
    <node name="ACMisc">0</node>
    <node name="TouchAC">11</node>
    <node name="FFAC">20</node>
    <node name="Init">+1</node>
    <node name="InitDex">1</node>
    <node name="InitMisc">0</node>
    <node name="Speed">20ft</node>
    <node name="TotalWeight">0.0</node>
    <node name="LightLoad">76</node>
    <node name="MediumLoad">153</node>
    <node name="HeavyLoad">230</node>
    <node name="LiftOverHead">230</node>
    <node name="LiftOffGround">460</node>
    <node name="LiftPushDrag">1150</node>
    <node name="Fort">+9</node>
    <node name="FortBase">3</node>
    <node name="FortAbility">4</node>
    <node name="FortMagic">0</node>
    <node name="FortMisc">2</node>
    <node name="FortTemp">0</node>
    <node name="Reflex">+3</node>
    <node name="ReflexBase">0</node>
    <node name="ReflexAbility">1</node>
    <node name="ReflexMagic">0</node>
    <node name="ReflexMisc">2</node>
    <node name="ReflexTemp">0</node>
    <node name="Will">+3</node>
    <node name="WillBase">0</node>
    <node name="WillAbility">1</node>
    <node name="WillMagic">0</node>
    <node name="WillMisc">2</node>
    <node name="WillTemp">0</node>
    <node name="MBAB">+5</node>
    <node name="MABBase">2</node>
    <node name="MABStr">3</node>
    <node name="MABSize">0</node>
    <node name="MABMisc">0</node>
    <node name="MABTemp">0</node>
    <node name="GBAB">+5</node>
    <node name="GABStr">3</node>
    <node name="GABSize">0</node>
    <node name="GABMisc">0</node>
    <node name="GABTemp">0</node>
    <node name="RBAB">+1</node>
    <node name="RABBase">0</node>
    <node name="RABDex">1</node>
    <node name="RABSize">0</node>
    <node name="RABMisc">0</node>
    <node name="RABTemp">0</node>
    <node name="Wep1Disp">on</node>
    <node name="Arm1Disp">on</node>
    <node name="Arm2Disp">on</node>
    <node name="Weapon1">Masterwork dwarven waraxe</node>
    <node name="Weapon1Wielded">on</node>
    <node name="Weapon1Carried">on</node>
    <node name="Weapon1AB">5</node>
    <node name="Weapon1Damage">1d10</node>
    <node name="Weapon11Crit">20X3</node>
    <node name="Armor1Name">Masterwork breastplate</node>
    <node name="Armor1Worn">on</node>
    <node name="Armor1Carried">on</node>
    <node name="Armor1Bonus">6</node>
    <node name="Armor1Check">-3</node>
    <node name="Armor1Dex">3</node>
    <node name="Armor2Name">Tower shield</node>
    <node name="Armor2Worn">on</node>
    <node name="Armor2Carried">on</node>
    <node name="Armor2Bonus">4</node>
    <node name="Armor2Check">-10</node>
    <node name="Armor2Dex">2</node>
    <node name="MaxRank">2</node>
    <node name="MaxRankCC">2</node>
    <node name="Skill01">Acrobatics</node>
    <node name="Skill01Ab">Dex</node>
    <node name="Skill01Mod">-12</node>
    <node name="Skill01AbMod">1</node>
    <node name="Skill01Rank">0</node>
    <node name="Skill01MiscMod">0</node>
    <node name="Skill01CheckPen">-13</node>
    <node name="Skill02">Appraise</node>
    <node name="Skill02Ab">Int</node>
    <node name="Skill02Mod">+2</node>
    <node name="Skill02AbMod">2</node>
    <node name="Skill02Rank">0</node>
    <node name="Skill02MiscMod">0</node>
    <node name="Skill02CheckPen">0</node>
    <node name="Skill03">Bluff</node>
    <node name="Skill03Ab">Cha</node>
    <node name="Skill03Mod">+0</node>
    <node name="Skill03AbMod">0</node>
    <node name="Skill03Rank">0</node>
    <node name="Skill03MiscMod">0</node>
    <node name="Skill03CheckPen">0</node>
    <node name="Skill04">Climb</node>
    <node name="Skill04Ab">Str</node>
    <node name="Skill04CC">on</node>
    <node name="Skill04Mod">-8</node>
    <node name="Skill04AbMod">3</node>
    <node name="Skill04Rank">2</node>
    <node name="Skill04MiscMod">0</node>
    <node name="Skill04CheckPen">-13</node>
    <node name="Skill05">Craft (armor)</node>
    <node name="Skill05Ab">Int</node>
    <node name="Skill05CC">on</node>
    <node name="Skill05Mod">+7</node>
    <node name="Skill05AbMod">2</node>
    <node name="Skill05Rank">5</node>
    <node name="Skill05MiscMod">0</node>
    <node name="Skill05CheckPen">0</node>
    <node name="Skill06">Diplomacy</node>
    <node name="Skill06Ab">Cha</node>
    <node name="Skill06Mod">+0</node>
    <node name="Skill06AbMod">0</node>
    <node name="Skill06Rank">0</node>
    <node name="Skill06MiscMod">0</node>
    <node name="Skill06CheckPen">0</node>
    <node name="Skill07">Disable Device</node>
    <node name="Skill07Ab">Int</node>
    <node name="Skill07Mod">+2</node>
    <node name="Skill07AbMod">2</node>
    <node name="Skill07Rank">0</node>
    <node name="Skill07MiscMod">0</node>
    <node name="Skill07CheckPen">0</node>
    <node name="Skill08">Disguise</node>
    <node name="Skill08Ab">Cha</node>
    <node name="Skill08Mod">+0</node>
    <node name="Skill08AbMod">0</node>
    <node name="Skill08Rank">0</node>
    <node name="Skill08MiscMod">0</node>
    <node name="Skill08CheckPen">0</node>
    <node name="Skill09">Escape Artist</node>
    <node name="Skill09Ab">Dex</node>
    <node name="Skill09Mod">-12</node>
    <node name="Skill09AbMod">1</node>
    <node name="Skill09Rank">0</node>
    <node name="Skill09MiscMod">0</node>
    <node name="Skill09CheckPen">-13</node>
    <node name="Skill10">Fly</node>
    <node name="Skill10Ab">Dex</node>
    <node name="Skill10Mod">-12</node>
    <node name="Skill10AbMod">1</node>
    <node name="Skill10Rank">0</node>
    <node name="Skill10MiscMod">0</node>
    <node name="Skill10CheckPen">-13</node>
    <node name="Skill11">Handle Animal</node>
    <node name="Skill11Ab">Cha</node>
    <node name="Skill11CC">on</node>
    <node name="Skill11Mod">+0</node>
    <node name="Skill11AbMod">0</node>
    <node name="Skill11Rank">0</node>
    <node name="Skill11MiscMod">0</node>
    <node name="Skill11CheckPen">0</node>
    <node name="Skill12">Heal</node>
    <node name="Skill12Ab">Wis</node>
    <node name="Skill12Mod">+1</node>
    <node name="Skill12AbMod">1</node>
    <node name="Skill12Rank">0</node>
    <node name="Skill12MiscMod">0</node>
    <node name="Skill12CheckPen">0</node>
    <node name="Skill13">Intimidate</node>
    <node name="Skill13Ab">Cha</node>
    <node name="Skill13CC">on</node>
    <node name="Skill13Mod">+5</node>
    <node name="Skill13AbMod">0</node>
    <node name="Skill13Rank">5</node>
    <node name="Skill13MiscMod">0</node>
    <node name="Skill13CheckPen">0</node>
    <node name="Skill14">Knowledge: Arcana</node>
    <node name="Skill14Ab">Int</node>
    <node name="Skill14Mod">+2</node>
    <node name="Skill14AbMod">2</node>
    <node name="Skill14Rank">0</node>
    <node name="Skill14MiscMod">0</node>
    <node name="Skill14CheckPen">0</node>
    <node name="Skill15">Knowledge: Architecture</node>
    <node name="Skill15Ab">Int</node>
    <node name="Skill15CC">on</node>
    <node name="Skill15Mod">+2</node>
    <node name="Skill15AbMod">2</node>
    <node name="Skill15Rank">0</node>
    <node name="Skill15MiscMod">0</node>
    <node name="Skill15CheckPen">0</node>
    <node name="Skill16">Knowledge: Dungeoneering</node>
    <node name="Skill16Ab">Int</node>
    <node name="Skill16CC">on</node>
    <node name="Skill16Mod">+5</node>
    <node name="Skill16AbMod">2</node>
    <node name="Skill16Rank">3</node>
    <node name="Skill16MiscMod">0</node>
    <node name="Skill16CheckPen">0</node>
    <node name="Skill17">Knowledge: Geography</node>
    <node name="Skill17Ab">Int</node>
    <node name="Skill17Mod">+2</node>
    <node name="Skill17AbMod">2</node>
    <node name="Skill17Rank">0</node>
    <node name="Skill17MiscMod">0</node>
    <node name="Skill17CheckPen">0</node>
    <node name="Skill18">Knowledge: History</node>
    <node name="Skill18Ab">Int</node>
    <node name="Skill18Mod">+4</node>
    <node name="Skill18AbMod">2</node>
    <node name="Skill18Rank">2</node>
    <node name="Skill18MiscMod">0</node>
    <node name="Skill18CheckPen">0</node>
    <node name="Skill19">Knowledge: Local</node>
    <node name="Skill19Ab">Int</node>
    <node name="Skill19Mod">+3</node>
    <node name="Skill19AbMod">2</node>
    <node name="Skill19Rank">1</node>
    <node name="Skill19MiscMod">0</node>
    <node name="Skill19CheckPen">0</node>
    <node name="Skill20">Knowledge: Nature</node>
    <node name="Skill20Ab">Int</node>
    <node name="Skill20Mod">+2</node>
    <node name="Skill20AbMod">2</node>
    <node name="Skill20Rank">0</node>
    <node name="Skill20MiscMod">0</node>
    <node name="Skill20CheckPen">0</node>
    <node name="Skill21">Knowledge: Nobility</node>
    <node name="Skill21Ab">Int</node>
    <node name="Skill21Mod">+2</node>
    <node name="Skill21AbMod">2</node>
    <node name="Skill21Rank">0</node>
    <node name="Skill21MiscMod">0</node>
    <node name="Skill21CheckPen">0</node>
    <node name="Skill22">Knowledge: Religion</node>
    <node name="Skill22Ab">Int</node>
    <node name="Skill22Mod">+2</node>
    <node name="Skill22AbMod">2</node>
    <node name="Skill22Rank">0</node>
    <node name="Skill22MiscMod">0</node>
    <node name="Skill22CheckPen">0</node>
    <node name="Skill23">Knowledge: The Planes</node>
    <node name="Skill23Ab">Int</node>
    <node name="Skill23Mod">+2</node>
    <node name="Skill23AbMod">2</node>
    <node name="Skill23Rank">0</node>
    <node name="Skill23MiscMod">0</node>
    <node name="Skill23CheckPen">0</node>
    <node name="Skill24">Linguistics</node>
    <node name="Skill24Ab">Int</node>
    <node name="Skill24Mod">+2</node>
    <node name="Skill24AbMod">2</node>
    <node name="Skill24Rank">0</node>
    <node name="Skill24MiscMod">0</node>
    <node name="Skill24CheckPen">0</node>
    <node name="Skill25">Perception</node>
    <node name="Skill25Ab">Wis</node>
    <node name="Skill25Mod">+1</node>
    <node name="Skill25AbMod">1</node>
    <node name="Skill25Rank">0</node>
    <node name="Skill25MiscMod">0</node>
    <node name="Skill25CheckPen">0</node>
    <node name="Skill26">Perform</node>
    <node name="Skill26Ab">Cha</node>
    <node name="Skill26Mod">+0</node>
    <node name="Skill26AbMod">0</node>
    <node name="Skill26Rank">0</node>
    <node name="Skill26MiscMod">0</node>
    <node name="Skill26CheckPen">0</node>
    <node name="Skill27">Profession</node>
    <node name="Skill27Ab">Wis</node>
    <node name="Skill27CC">on</node>
    <node name="Skill27Mod">+1</node>
    <node name="Skill27AbMod">1</node>
    <node name="Skill27Rank">0</node>
    <node name="Skill27MiscMod">0</node>
    <node name="Skill27CheckPen">0</node>
    <node name="Skill28">Ride</node>
    <node name="Skill28Ab">Dex</node>
    <node name="Skill28CC">on</node>
    <node name="Skill28Mod">+5</node>
    <node name="Skill28AbMod">1</node>
    <node name="Skill28Rank">4</node>
    <node name="Skill28MiscMod">0</node>
    <node name="Skill28CheckPen">0</node>
    <node name="Skill29">Sense Motive</node>
    <node name="Skill29Ab">Wis</node>
    <node name="Skill29Mod">+1</node>
    <node name="Skill29AbMod">1</node>
    <node name="Skill29Rank">0</node>
    <node name="Skill29MiscMod">0</node>
    <node name="Skill29CheckPen">0</node>
    <node name="Skill30">Sleight of Hand</node>
    <node name="Skill30Ab">Dex</node>
    <node name="Skill30Mod">-12</node>
    <node name="Skill30AbMod">1</node>
    <node name="Skill30Rank">0</node>
    <node name="Skill30MiscMod">0</node>
    <node name="Skill30CheckPen">-13</node>
    <node name="Skill31">Spellcraft</node>
    <node name="Skill31Ab">Int</node>
    <node name="Skill31Mod">+2</node>
    <node name="Skill31AbMod">2</node>
    <node name="Skill31Rank">0</node>
    <node name="Skill31MiscMod">0</node>
    <node name="Skill31CheckPen">0</node>
    <node name="Skill32">Stealth</node>
    <node name="Skill32Ab">Dex</node>
    <node name="Skill32Mod">-12</node>
    <node name="Skill32AbMod">1</node>
    <node name="Skill32Rank">0</node>
    <node name="Skill32MiscMod">0</node>
    <node name="Skill32CheckPen">-13</node>
    <node name="Skill33">Survival</node>
    <node name="Skill33Ab">Wis</node>
    <node name="Skill33CC">on</node>
    <node name="Skill33Mod">+1</node>
    <node name="Skill33AbMod">1</node>
    <node name="Skill33Rank">0</node>
    <node name="Skill33MiscMod">0</node>
    <node name="Skill33CheckPen">0</node>
    <node name="Skill34">Swim</node>
    <node name="Skill34Ab">Str</node>
    <node name="Skill34CC">on</node>
    <node name="Skill34Mod">-23</node>
    <node name="Skill34AbMod">3</node>
    <node name="Skill34Rank">0</node>
    <node name="Skill34MiscMod">0</node>
    <node name="Skill34CheckPen">-26</node>
    <node name="Skill35">Use Magic Device</node>
    <node name="Skill35Ab">Cha</node>
    <node name="Skill35Mod">+0</node>
    <node name="Skill35AbMod">0</node>
    <node name="Skill35Rank">0</node>
    <node name="Skill35MiscMod">0</node>
    <node name="Skill35CheckPen">0</node>
    <node name="Feat01">Toughness</node>
    <node name="Feat02">Endurance</node>
    <node name="Feat03">Weapon focus (Dwarven waraxe)</node>
    <node name="Feat16">Dwarven traits</node>
    <node name="Feat17">Bravery</node>
    <node name="Gear01">Masterwork Breastplate</node>
    <node name="Gear02">Masterwork dwarven waraxe</node>
    <node name="Gear03">Tower shield</node>
    <node name="MagicDisp">on</node>
    <node name="CashPP">0</node>
    <node name="CashPPParty">0</node>
    <node name="CashGP">190</node>
    <node name="CashGPParty">0</node>
    <node name="CashSP">0</node>
    <node name="CashSPParty">0</node>
    <node name="CashCP">0</node>
    <node name="CashCPParty">0</node>
    <node name="CashTotal">190</node>
    <node name="CashTotalParty">0</node>
  </data>
</character>
